morshutalk/__init__.py
morshutalk/__main__.py
morshutalk/morshu.py
morshutalk/morshu.wav
morshutalkgui/__init__.py
morshutalkgui/__main__.py
morshutalkgui/mainwindow.py
morshutalkgui/res_rc.py
morshutalkgui/ui_mainwindow.py
MorshuTalk-0.0.1.dist-info/LICENSE.txt
MorshuTalk-0.0.1.dist-info/METADATA
MorshuTalk-0.0.1.dist-info/WHEEL
MorshuTalk-0.0.1.dist-info/entry_points.txt
MorshuTalk-0.0.1.dist-info/top_level.txt
MorshuTalk-0.0.1.dist-info/RECORD
