Metadata-Version: 2.1
Name: MorshuTalk
Version: 0.0.1
Summary: Morshu text-to-speech
Home-page: https://github.com/n0spaces/MorshuTalk
Author: n0spaces
License: UNKNOWN
Platform: UNKNOWN
Classifier: Programming Language :: Python :: 3
Classifier: License :: OSI Approved :: MIT License
Classifier: Operating System :: OS Independent
Requires-Python: >=3.7
License-File: LICENSE.txt
Requires-Dist: g2p-en
Requires-Dist: numpy
Requires-Dist: pydub
Requires-Dist: sounddevice
